mappy/__init__.py
mappy/kakao.py
mappy/mappy.py
mappy/naver.py
mappy/tmap.py
mappy/error/__init__.py
mappy/error/base.py
mappy/types/__init__.py
mappy/types/address.py
mappy/types/point.py
L_mappy-0.1.0.dist-info/METADATA
L_mappy-0.1.0.dist-info/WHEEL
L_mappy-0.1.0.dist-info/top_level.txt
L_mappy-0.1.0.dist-info/RECORD
