Metadata-Version: 2.1
Name: L-mappy
Version: 0.1.0
Summary: Mappy는 위치 기반 기능을 제공하는 파이썬 라이브러리로, 주소를 좌표로 변환하는 지오코딩(geocoding), 좌표에서 주소 정보를 얻는 지오로케이션(geolocation), 두 지점 간의 경로를 계산하는 방향(directions) 정보 제공 기능을 포함하고 있습니다.
Home-page: https://github.com/gunhe17/l-mappy
Author: L
Author-email: pers.gun17@gmail.com
Requires-Dist: dotenv
Requires-Dist: requests
